collective.taxonomy-3.1.7-py3.13-nspkg.pth
collective/taxonomy/__init__.py
collective/taxonomy/behavior.py
collective/taxonomy/browser.py
collective/taxonomy/collectionfilter.py
collective/taxonomy/configure.zcml
collective/taxonomy/controlpanel.py
collective/taxonomy/edit_taxonomy_data.pt
collective/taxonomy/exportimport.py
collective/taxonomy/factory.py
collective/taxonomy/generated.py
collective/taxonomy/i18n.py
collective/taxonomy/indexer.py
collective/taxonomy/interfaces.py
collective/taxonomy/jsonimpl.py
collective/taxonomy/listing_tabular.pt
collective/taxonomy/rebuild_i18n.sh
collective/taxonomy/setuphandlers.py
collective/taxonomy/testing.py
collective/taxonomy/testing.zcml
collective/taxonomy/upgradesteps.py
collective/taxonomy/upgradesteps.zcml
collective/taxonomy/utility.py
collective/taxonomy/vdex.py
collective/taxonomy/vocabulary.py
collective/taxonomy/widget.py
collective/taxonomy/widget.zcml
collective/taxonomy/widget_display.pt
collective/taxonomy/widget_input.pt
collective/taxonomy/locales/collective.taxonomy.pot
collective/taxonomy/locales/da/LC_MESSAGES/collective.taxonomy.mo
collective/taxonomy/locales/da/LC_MESSAGES/collective.taxonomy.po
collective/taxonomy/locales/de/LC_MESSAGES/collective.taxonomy.mo
collective/taxonomy/locales/de/LC_MESSAGES/collective.taxonomy.po
collective/taxonomy/locales/es/LC_MESSAGES/collective.taxonomy.mo
collective/taxonomy/locales/es/LC_MESSAGES/collective.taxonomy.po
collective/taxonomy/locales/fr/LC_MESSAGES/collective.taxonomy.mo
collective/taxonomy/locales/fr/LC_MESSAGES/collective.taxonomy.po
collective/taxonomy/locales/it/LC_MESSAGES/collective.taxonomy.mo
collective/taxonomy/locales/it/LC_MESSAGES/collective.taxonomy.po
collective/taxonomy/locales/nl/LC_MESSAGES/collective.taxonomy.mo
collective/taxonomy/locales/nl/LC_MESSAGES/collective.taxonomy.po
collective/taxonomy/profiles/default/browserlayer.xml
collective/taxonomy/profiles/default/controlpanel.xml
collective/taxonomy/profiles/default/metadata.xml
collective.taxonomy-3.1.7.dist-info/METADATA
collective.taxonomy-3.1.7.dist-info/WHEEL
collective.taxonomy-3.1.7.dist-info/entry_points.txt
collective.taxonomy-3.1.7.dist-info/namespace_packages.txt
collective.taxonomy-3.1.7.dist-info/top_level.txt
collective.taxonomy-3.1.7.dist-info/RECORD
