Metadata-Version: 2.2
Name: collective.taxonomy
Version: 3.1.7
Summary: Create, edit and use hierarchical taxonomies in Plone!
Home-page: https://pypi.org/project/collective.taxonomy/
Author: Bo Simonsen and Malthe Borch
Author-email: bo@headnet.dk
License: GPLv2+
Keywords: plone taxonomy dexterity
Classifier: Development Status :: 6 - Mature
Classifier: Environment :: Web Environment
Classifier: Framework :: Plone
Classifier: Framework :: Plone :: 6.0
Classifier: Framework :: Plone :: 6.1
Classifier: Framework :: Plone :: Addon
Classifier: Framework :: Zope
Classifier: Framework :: Zope :: 5
Classifier: License :: OSI Approved :: GNU General Public License v2 or later (GPLv2+)
Classifier: Programming Language :: Python
Classifier: Programming Language :: Python :: 3.9
Classifier: Programming Language :: Python :: 3.10
Classifier: Programming Language :: Python :: 3.11
Classifier: Programming Language :: Python :: 3.12
Classifier: Programming Language :: Python :: 3.13
Requires-Python: >=3.9
Requires-Dist: setuptools
Requires-Dist: plone.base
Requires-Dist: plone.supermodel
Requires-Dist: plone.api>=1.5
Requires-Dist: plone.app.registry
Requires-Dist: plone.app.dexterity
Requires-Dist: lxml
Provides-Extra: dev
Requires-Dist: zest.releaser[recommended]; extra == "dev"
Provides-Extra: test
Requires-Dist: mock; extra == "test"
Requires-Dist: plone.api; extra == "test"
Requires-Dist: plone.app.caching; extra == "test"
Requires-Dist: plone.app.contenttypes; extra == "test"
Requires-Dist: plone.app.contenttypes[test]; extra == "test"
Requires-Dist: plone.app.iterate; extra == "test"
Requires-Dist: plone.app.querystring; extra == "test"
Requires-Dist: plone.app.robotframework[debug]; extra == "test"
Requires-Dist: plone.app.testing; extra == "test"
Requires-Dist: plone.restapi[test]; extra == "test"
Requires-Dist: plone.testing; extra == "test"
Requires-Dist: requests; extra == "test"
Dynamic: author
Dynamic: author-email
Dynamic: classifier
Dynamic: description
Dynamic: home-page
Dynamic: keywords
Dynamic: license
Dynamic: provides-extra
Dynamic: requires-dist
Dynamic: requires-python
Dynamic: summary
